not_gitmodules/__init__.py
not_gitmodules/cli.py
not_gitmodules/core.py
not_gitmodules/parts/__init__.py
not_gitmodules/parts/clean_repo.py
not_gitmodules/parts/clone_repo.py
not_gitmodules/parts/delete_git.py
not_gitmodules/parts/directory_create.py
not_gitmodules/parts/directory_rename.py
not_gitmodules/parts/get_repo_name.py
not_gitmodules/parts/move_folder.py
not_gitmodules/parts/yaml_reader.py
not_gitmodules-0.4.4.dist-info/LICENSE
not_gitmodules-0.4.4.dist-info/METADATA
not_gitmodules-0.4.4.dist-info/WHEEL
not_gitmodules-0.4.4.dist-info/entry_points.txt
not_gitmodules-0.4.4.dist-info/top_level.txt
not_gitmodules-0.4.4.dist-info/RECORD
