Metadata-Version: 2.1
Name: not_gitmodules
Version: 0.4.4
Summary: A library for managing git repositories in a directory.
Home-page: https://github.com/Armen-Jean-Andreasian/not_gitmodules
Author: Armen-Jean Andreasian
Author-email: armen_andreasian@proton.me
License: Custom License
Classifier: Programming Language :: Python :: 3
Classifier: License :: Other/Proprietary License
Classifier: Operating System :: OS Independent
License-File: LICENSE
Requires-Dist: pyyaml
